patchwork/node/__init__.py
patchwork/node/contrib/__init__.py
patchwork/node/contrib/pydantic.py
patchwork/node/contrib/tortoise.py
patchwork/node/core/__init__.py
patchwork/node/core/dependencies.py
patchwork/node/core/exceptions.py
patchwork/node/core/module.py
patchwork/node/core/router.py
patchwork/node/core/worker.py
patchwork/node/executor/__init__.py
patchwork/node/executor/base.py
patchwork/node/executor/unit/__init__.py
patchwork/node/executor/unit/base.py
patchwork/node/executor/unit/inline.py
patchwork/node/executor/unit/threads.py
patchwork/node/manager/__init__.py
patchwork/node/manager/base.py
patchwork/node/manager/http.py
patchwork/node/testutils/__init__.py
patchwork/node/testutils/worker.py
tests/__init__.py
tests/conftest.py
tests/message.py
tests/router.py
tests/test_exception_handlers.py
tests/test_executor.py
tests/test_inlineunit.py
tests/test_node.py
tests/test_router.py
tests/test_worker.py
tests/testutils/__init__.py
tests/testutils/test_catcher.py
tests/testutils/test_worker.py
patchwork_node-0.2.5.dist-info/LICENSE
patchwork_node-0.2.5.dist-info/METADATA
patchwork_node-0.2.5.dist-info/WHEEL
patchwork_node-0.2.5.dist-info/top_level.txt
patchwork_node-0.2.5.dist-info/RECORD
